{
  "type": "FeatureCollection",
  "features": [
    {
      "type": "Feature",
      "properties": {
        "name": "Stepanakert",
        "type": "City",
        "country": "nagorno-karabakh",
        "visited": true
      },
      "geometry": {
        "type": "Point",
        "coordinates": [
          46.778411865234375,
          39.81170080625295
        ]
      }
    },
    {
      "type": "Feature",
      "properties": {
        "name": "Shushi",
        "type": "City",
        "country": "nagorno-karabakh",
        "visited": true
      },
      "geometry": {
        "type": "Point",
        "coordinates": [
          46.750946044921875,
          39.756296389617624
        ]
      }
    }
  ]
}